Metadata-Version: 2.1
Name: Magiccal
Version: 1.0.0
Summary: Calculate 11 different complex calculations like Data, BMI, GST, Discount, Date, Age, Time, Decimal, Temperature, Speed, Pressure
Home-page: http://ashishjaiswal.great-site.net/
Author: Ashish Jaiswal
Author-email: a.j250897@gmail.com
License: MIT
Project-URL: Source Code, https://github.com/itsashishjaiswal/PythonLibraries/tree/main/MagiccalLibrary
Keywords: python,education,calculations,conversions,magiccal,data
Platform: UNKNOWN
Classifier: Development Status :: 5 - Production/Stable
Classifier: Intended Audience :: Education
Classifier: Operating System :: OS Independent
Classifier: License :: OSI Approved :: MIT License
Classifier: Programming Language :: Python :: 3
License-File: LICENSE.txt
